yuseful_prompts/__init__.py
yuseful_prompts/chains.py
yuseful_prompts/llms.py
yuseful_prompts/prompts.py
yuseful_prompts/tests/__init__.py
yuseful_prompts/tests/test_category_chains.py
yuseful_prompts/tests/test_headline_chains.py
yuseful_prompts/tests/test_misc_chains.py
yuseful_prompts-4.0.7.dist-info/LICENSE
yuseful_prompts-4.0.7.dist-info/METADATA
yuseful_prompts-4.0.7.dist-info/WHEEL
yuseful_prompts-4.0.7.dist-info/top_level.txt
yuseful_prompts-4.0.7.dist-info/RECORD
