Metadata-Version: 2.1
Name: yuseful_prompts
Version: 4.0.7
Summary: tested chains for common use-cases of the markets-agent.com using open LLMs with ollama and Langchain
Home-page: https://github.com/markets-agent/yuseful_prompts
Author: yactouat
Author-email: yactouat@yactouat.com
License: MIT
License-File: LICENSE
Requires-Dist: langchain-core
Requires-Dist: langchain-community
Requires-Dist: langchain-ollama
Requires-Dist: pytest
